cdktf_cdktf_provider_googleworkspace/__init__.py
cdktf_cdktf_provider_googleworkspace/py.typed
cdktf_cdktf_provider_googleworkspace/_jsii/__init__.py
cdktf_cdktf_provider_googleworkspace/_jsii/provider-googleworkspace@8.0.1.jsii.tgz
cdktf_cdktf_provider_googleworkspace/chrome_policy/__init__.py
cdktf_cdktf_provider_googleworkspace/data_googleworkspace_chrome_policy_schema/__init__.py
cdktf_cdktf_provider_googleworkspace/data_googleworkspace_domain/__init__.py
cdktf_cdktf_provider_googleworkspace/data_googleworkspace_domain_alias/__init__.py
cdktf_cdktf_provider_googleworkspace/data_googleworkspace_group/__init__.py
cdktf_cdktf_provider_googleworkspace/data_googleworkspace_group_member/__init__.py
cdktf_cdktf_provider_googleworkspace/data_googleworkspace_group_members/__init__.py
cdktf_cdktf_provider_googleworkspace/data_googleworkspace_group_settings/__init__.py
cdktf_cdktf_provider_googleworkspace/data_googleworkspace_groups/__init__.py
cdktf_cdktf_provider_googleworkspace/data_googleworkspace_org_unit/__init__.py
cdktf_cdktf_provider_googleworkspace/data_googleworkspace_privileges/__init__.py
cdktf_cdktf_provider_googleworkspace/data_googleworkspace_role/__init__.py
cdktf_cdktf_provider_googleworkspace/data_googleworkspace_schema/__init__.py
cdktf_cdktf_provider_googleworkspace/data_googleworkspace_user/__init__.py
cdktf_cdktf_provider_googleworkspace/data_googleworkspace_users/__init__.py
cdktf_cdktf_provider_googleworkspace/domain/__init__.py
cdktf_cdktf_provider_googleworkspace/domain_alias/__init__.py
cdktf_cdktf_provider_googleworkspace/gmail_send_as_alias/__init__.py
cdktf_cdktf_provider_googleworkspace/group/__init__.py
cdktf_cdktf_provider_googleworkspace/group_member/__init__.py
cdktf_cdktf_provider_googleworkspace/group_members/__init__.py
cdktf_cdktf_provider_googleworkspace/group_settings/__init__.py
cdktf_cdktf_provider_googleworkspace/org_unit/__init__.py
cdktf_cdktf_provider_googleworkspace/provider/__init__.py
cdktf_cdktf_provider_googleworkspace-8.0.1.dist-info/LICENSE
cdktf_cdktf_provider_googleworkspace-8.0.1.dist-info/METADATA
cdktf_cdktf_provider_googleworkspace-8.0.1.dist-info/WHEEL
cdktf_cdktf_provider_googleworkspace-8.0.1.dist-info/top_level.txt
cdktf_cdktf_provider_googleworkspace-8.0.1.dist-info/RECORD
